README.md
setup.py
gradient_descent/Adam.py
gradient_descent/ExceptionHandler.py
gradient_descent/GradientDescent.py
gradient_descent/Momentum.py
gradient_descent/NAG.py
gradient_descent/RMSprop.py
gradient_descent/__init__.py
gradient_descent.egg-info/PKG-INFO
gradient_descent.egg-info/SOURCES.txt
gradient_descent.egg-info/dependency_links.txt
gradient_descent.egg-info/top_level.txt
tests/__init__.py
tests/test_adam.py
tests/test_gradientdescent.py
tests/test_momentum.py
tests/test_nag.py
tests/test_rmsprop.py