Metadata-Version: 2.1
Name: gradient-descent
Version: 0.0.3
Summary: Package for applying gradient descent optimization algorithms
Home-page: https://github.com/DanielDaCosta/optimization-algorithms
Author: Daniel da Costa
Author-email: daniel.pereiracosta@hotmail.com
License: UNKNOWN
Platform: UNKNOWN
Classifier: Programming Language :: Python :: 3
Classifier: License :: OSI Approved :: MIT License
Classifier: Operating System :: OS Independent
Requires-Python: >=3.6
